TGNLP/__init__.py
TGNLP-1.0.1.dist-info/LICENSE
TGNLP-1.0.1.dist-info/METADATA
TGNLP-1.0.1.dist-info/WHEEL
TGNLP-1.0.1.dist-info/top_level.txt
TGNLP-1.0.1.dist-info/RECORD
