Metadata-Version: 2.1
Name: TGNLP
Version: 1.0.1
Summary: A text analysis/feature generation tool for english text, or text corpuses
Author-email: Jesse Coulson <jesseccoulson@gmail.com>, Primrose Johns <primrose.johns.1@gmail.com>
Project-URL: Homepage, https://github.com/Primrose-Johns/TGNLP
Classifier: Programming Language :: Python :: 3
Classifier: License :: OSI Approved :: MIT License
Classifier: Operating System :: OS Independent
Classifier: Development Status :: 5 - Production/Stable
Requires-Python: >=3.9.2
License-File: LICENSE
Requires-Dist: pandas
Requires-Dist: networkx
Requires-Dist: gensim
Requires-Dist: scipy ==1.10.1
Requires-Dist: matplotlib
Requires-Dist: scikit-learn
Requires-Dist: numpy
Requires-Dist: spacy
Requires-Dist: reportlab
Requires-Dist: nltk
